README.rst
setup.py
django_kittens/__init__.py
django_kittens/apps.py
django_kittens/constants.py
django_kittens/models.py
django_kittens/urls.py
django_kittens/version.py
django_kittens/views.py
django_kittens.egg-info/PKG-INFO
django_kittens.egg-info/SOURCES.txt
django_kittens.egg-info/dependency_links.txt
django_kittens.egg-info/not-zip-safe
django_kittens.egg-info/requires.txt
django_kittens.egg-info/top_level.txt
django_kittens/migrations/0001_initial.py
django_kittens/migrations/__init__.py
django_kittens/static/kittens/kitten.css
django_kittens/templates/kittens/base.html
django_kittens/templates/kittens/kitten_down.html
django_kittens/templates/kittens/kitten_up.html
django_kittens/templates/kittens/random.html
django_kittens/templates/kittens/top.html
django_kittens/tests/__init__.py
django_kittens/tests/models_tests.py
django_kittens/tests/test_models.py