Metadata-Version: 1.1
Name: django-kittens
Version: 0.1.3
Summary: Add kittens and kitten voting to your django project!
Home-page: https://github.com/Wilduck/django-kittens
Author: Erik Swanson
Author-email: TheErikSwanson@gmail.com
License: MIT
Platform: UNKNOWN
Classifier: Programming Language :: Python
Classifier: Programming Language :: Python :: 3.4
Classifier: Intended Audience :: Developers
Classifier: License :: OSI Approved :: MIT License
Classifier: Operating System :: OS Independent
Classifier: Framework :: Django :: 1.8
